autodistill_gcp_vision/__init__.py
autodistill_gcp_vision/gcp_vision_model.py
autodistill_gcp_vision-0.1.0.dist-info/LICENSE
autodistill_gcp_vision-0.1.0.dist-info/METADATA
autodistill_gcp_vision-0.1.0.dist-info/WHEEL
autodistill_gcp_vision-0.1.0.dist-info/top_level.txt
autodistill_gcp_vision-0.1.0.dist-info/RECORD
