Metadata-Version: 2.1
Name: autodistill-gcp-vision
Version: 0.1.0
Summary: Autodistill Google Cloud Vision module for use in training a custom, fine-tuned model.
Home-page: https://github.com/capjamesg/autodistill-gcp-vision
Author: Roboflow
Author-email: support@roboflow.com
Classifier: Programming Language :: Python :: 3
Classifier: License :: OSI Approved :: MIT License
Classifier: Operating System :: OS Independent
Requires-Python: >=3.7
License-File: LICENSE
Requires-Dist: google-cloud-vision
Requires-Dist: autodistill
Requires-Dist: supervision
Requires-Dist: numpy
Provides-Extra: dev
Requires-Dist: flake8 ; extra == 'dev'
Requires-Dist: black ==22.3.0 ; extra == 'dev'
Requires-Dist: isort ; extra == 'dev'
Requires-Dist: twine ; extra == 'dev'
Requires-Dist: pytest ; extra == 'dev'
Requires-Dist: wheel ; extra == 'dev'
